ansible_playbook_runner/__init__.py
ansible_playbook_runner-0.1.2.dist-info/METADATA
ansible_playbook_runner-0.1.2.dist-info/WHEEL
ansible_playbook_runner-0.1.2.dist-info/top_level.txt
ansible_playbook_runner-0.1.2.dist-info/RECORD
