Metadata-Version: 2.1
Name: ansible-playbook-runner
Version: 0.1.2
Summary: simple ansible playbook runner
Home-page: UNKNOWN
Author: Avi Naftalis
Author-email: anaftalis@gmail.com
License: UNKNOWN
Platform: UNKNOWN
Requires-Dist: ansible (>=2)
